logpyseq.py
logpyseq-0.1.1.dist-info/LICENSE
logpyseq-0.1.1.dist-info/METADATA
logpyseq-0.1.1.dist-info/WHEEL
logpyseq-0.1.1.dist-info/top_level.txt
logpyseq-0.1.1.dist-info/RECORD
