Metadata-Version: 2.1
Name: logpyseq
Version: 0.1.1
Summary: Pythonic wrapper for LogSeq API
Requires-Python: >=3.10
License-File: LICENSE
Requires-Dist: requests >=2.32.3
